{
  "products": [
    {
      "title": "farda",
      "compra": false,
      "id": "d8db",
      "userId": "auth0|123"
    },
    {
      "id": "e545",
      "title": "Chapeu",
      "compra": true,
      "userId": "auth0|123"
    },
    {
      "id": "cfd6",
      "title": "caneca",
      "compra": false,
      "userId": "auth0|456"
    },
    {
      "id": "5922",
      "title": "gol",
      "compra": false
    },
    {
      "id": "105c",
      "title": "davi",
      "compra": false
    },
    {
      "id": "c309",
      "title": "lista",
      "compra": true
    },
    {
      "id": "1f7b",
      "title": "fas",
      "compra": true
    },
    {
      "id": "1b93",
      "title": "sad",
      "compra": false
    },
    {
      "id": "f069",
      "title": "testando",
      "compra": true
    },
    {
      "id": "1b23",
      "title": "das",
      "compra": true
    },
    {
      "id": "5bef",
      "title": "zezo",
      "compra": false
    },
    {
      "id": "df21",
      "title": "dava",
      "compra": false
    },
    {
      "id": "bbaa",
      "title": "ddd",
      "compra": false
    }
  ]
}